WUDESIM_Py/WUDESIM_LIB.dll
WUDESIM_Py/__init__.py
WUDESIM_Py/epanet2.dll
WUDESIM_Py/src.py
WUDESIM_Py-0.2.3.data/data/WUDESIM_Py/WUDESIM_LIB.dll
WUDESIM_Py-0.2.3.data/data/WUDESIM_Py/epanet2.dll
WUDESIM_Py-0.2.3.dist-info/LICENSE
WUDESIM_Py-0.2.3.dist-info/METADATA
WUDESIM_Py-0.2.3.dist-info/WHEEL
WUDESIM_Py-0.2.3.dist-info/top_level.txt
WUDESIM_Py-0.2.3.dist-info/RECORD
