Metadata-Version: 2.1
Name: WUDESIM-Py
Version: 0.2.3
Summary: A model for simulating water quality in the dead-end branches of drinking water distribution networks
Home-page: UNKNOWN
Author: Ahmed Abokifa
Author-email: abokifa@uic.edu
License: MIT license
Platform: UNKNOWN
